Metadata-Version: 2.1
Name: shuzhen
Version: 1.1.1
Summary: Just a test
Home-page: https://github.com/lishuzhen97/lishuzhen
Author: Li shuzhen
Author-email: shuzhen_li97@163.com
License: MIT
Platform: UNKNOWN
